[
  {
    "ContainingType": "WebApi.Controllers.AuthenticationController",
    "Method": "Login",
    "RelativePath": "api/authentication/login",
    "HttpMethod": "POST",
    "IsController": true,
    "Order": 0,
    "Parameters": [
      {
        "Name": "request",
        "Type": "Application.Authentication.Login.LoginRequest",
        "IsRequired": true
      }
    ],
    "ReturnTypes": [
      {
        "Type": "Application.Authentication.Login.LoginResponse",
        "MediaTypes": [
          "text/plain",
          "application/json",
          "text/json"
        ],
        "StatusCode": 200
      }
    ]
  },
  {
    "ContainingType": "WebApi.Controllers.StocksController",
    "Method": "GetList",
    "RelativePath": "api/stocks",
    "HttpMethod": "GET",
    "IsController": true,
    "Order": 0,
    "Parameters": [
      {
        "Name": "Name",
        "Type": "System.String",
        "IsRequired": false
      }
    ],
    "ReturnTypes": [
      {
        "Type": "System.Collections.Generic.IEnumerable\u00601[[Application.Stocks.GetList.GetListItemResponse, Application, Version=1.0.0.0, Culture=neutral, PublicKeyToken=null]]",
        "MediaTypes": [
          "text/plain",
          "application/json",
          "text/json"
        ],
        "StatusCode": 200
      }
    ]
  },
  {
    "ContainingType": "WebApi.Controllers.StocksController",
    "Method": "GetDetails",
    "RelativePath": "api/stocks/{symbol}/details",
    "HttpMethod": "GET",
    "IsController": true,
    "Order": 0,
    "Parameters": [
      {
        "Name": "symbol",
        "Type": "System.String",
        "IsRequired": true
      }
    ],
    "ReturnTypes": [
      {
        "Type": "Application.Stocks.GetDetails.GetDetailsResponse",
        "MediaTypes": [
          "text/plain",
          "application/json",
          "text/json"
        ],
        "StatusCode": 200
      }
    ]
  },
  {
    "ContainingType": "WebApi.Controllers.StocksController",
    "Method": "GetHistory",
    "RelativePath": "api/stocks/{symbol}/history",
    "HttpMethod": "GET",
    "IsController": true,
    "Order": 0,
    "Parameters": [
      {
        "Name": "symbol",
        "Type": "System.String",
        "IsRequired": true
      },
      {
        "Name": "Symbol",
        "Type": "System.String",
        "IsRequired": false
      },
      {
        "Name": "Start",
        "Type": "System.DateTimeOffset",
        "IsRequired": false
      },
      {
        "Name": "End",
        "Type": "System.DateTimeOffset",
        "IsRequired": false
      }
    ],
    "ReturnTypes": [
      {
        "Type": "System.Collections.Generic.IEnumerable\u00601[[Application.Stocks.GetHistory.GetHistoryCandle, Application, Version=1.0.0.0, Culture=neutral, PublicKeyToken=null]]",
        "MediaTypes": [
          "text/plain",
          "application/json",
          "text/json"
        ],
        "StatusCode": 200
      }
    ]
  },
  {
    "ContainingType": "WebApi.Controllers.UsersController",
    "Method": "Create",
    "RelativePath": "api/users",
    "HttpMethod": "POST",
    "IsController": true,
    "Order": 0,
    "Parameters": [
      {
        "Name": "request",
        "Type": "Application.Users.Create.CreateUserRequest",
        "IsRequired": true
      }
    ],
    "ReturnTypes": []
  }
]